[
  {
    "content_id": 220434,
    "title": "São Tomé und Príncipe: Reise- und Sicherheitshinweise",
    "country_name": "São Tomé und Príncipe",
    "country_code": "ST",
    "iso3_country_code": "STP",
    "last_modified_iso": "2025-03-20T09:49:25+00:00",
    "effective_iso": null,
    "warning": 0,
    "partial_warning": 0,
    "situation_warning": 0,
    "situation_part_warning": 0
  },
  {
    "content_id": 226660,
    "title": "Komoren: Reise- und Sicherheitshinweise",
    "country_name": "Komoren",
    "country_code": "KM",
    "iso3_country_code": "COM",
    "last_modified_iso": "2025-03-26T12:12:53+00:00",
    "effective_iso": null,
    "warning": 0,
    "partial_warning": 0,
    "situation_warning": 0,
    "situation_part_warning": 0
  },
  {
    "content_id": 226750,
    "title": "St. Lucia: Reise- und Sicherheitshinweise",
    "country_name": "St. Lucia",
    "country_code": "LC",
    "iso3_country_code": "LCA",
    "last_modified_iso": "2025-07-07T14:09:08+00:00",
    "effective_iso": null,
    "warning": 0,
    "partial_warning": 0,
    "situation_warning": 0,
    "situation_part_warning": 0
  },
  {
    "content_id": 222842,
    "title": "Mongolei: Reise- und Sicherheitshinweise",
    "country_name": "Mongolei",
    "country_code": "MN",
    "iso3_country_code": "MNG",
    "last_modified_iso": "2025-07-04T10:04:24+00:00",
    "effective_iso": null,
    "warning": 0,
    "partial_warning": 0,
    "situation_warning": 0,
    "situation_part_warning": 0
  },
  {
    "content_id": 206774,
    "title": "Turkmenistan: Reise- und Sicherheitshinweise",
    "country_name": "Turkmenistan",
    "country_code": "TM",
    "iso3_country_code": "TKM",
    "last_modified_iso": "2025-07-11T10:33:12+00:00",
    "effective_iso": null,
    "warning": 0,
    "partial_warning": 0,
    "situation_warning": 0,
    "situation_part_warning": 0
  },
  {
    "content_id": 226702,
    "title": "Bhutan: Reise- und Sicherheitshinweise",
    "country_name": "Bhutan",
    "country_code": "BT",
    "iso3_country_code": "BTN",
    "last_modified_iso": "2025-07-11T10:54:34+00:00",
    "effective_iso": null,
    "warning": 0,
    "partial_warning": 0,
    "situation_warning": 0,
    "situation_part_warning": 0
  },
  {
    "content_id": 226552,
    "title": "Cookinseln: Reise- und Sicherheitshinweise",
    "country_name": "Cookinseln",
    "country_code": "CK",
    "iso3_country_code": "COK",
    "last_modified_iso": "2025-07-11T11:56:35+00:00",
    "effective_iso": null,
    "warning": 0,
    "partial_warning": 0,
    "situation_warning": 0,
    "situation_part_warning": 0
  },
  {
    "content_id": 224964,
    "title": "Paraguay: Reise- und Sicherheitshinweise",
    "country_name": "Paraguay",
    "country_code": "PY",
    "iso3_country_code": "PRY",
    "last_modified_iso": "2025-07-11T12:29:44+00:00",
    "effective_iso": null,
    "warning": 0,
    "partial_warning": 0,
    "situation_warning": 0,
    "situation_part_warning": 0
  },
  {
    "content_id": 220316,
    "title": "Grenada: Reise- und Sicherheitshinweise",
    "country_name": "Grenada",
    "country_code": "GD",
    "iso3_country_code": "GRD",
    "last_modified_iso": "2025-05-16T09:26:23+00:00",
    "effective_iso": null,
    "warning": 0,
    "partial_warning": 0,
    "situation_warning": 0,
    "situation_part_warning": 0
  },
  {
    "content_id": 220300,
    "title": "Dominica: Reise- und Sicherheitshinweise",
    "country_name": "Dominica",
    "country_code": "DM",
    "iso3_country_code": "DMA",
    "last_modified_iso": "2025-05-15T13:43:27+00:00",
    "effective_iso": null,
    "warning": 0,
    "partial_warning": 0,
    "situation_warning": 0,
    "situation_part_warning": 0
  },
  {
    "content_id": 220650,
    "title": "Salomonen: Reise- und Sicherheitshinweise",
    "country_name": "Salomonen",
    "country_code": "SB",
    "iso3_country_code": "SLB",
    "last_modified_iso": "2025-08-01T10:18:54+00:00",
    "effective_iso": null,
    "warning": 0,
    "partial_warning": 0,
    "situation_warning": 0,
    "situation_part_warning": 0
  },
  {
    "content_id": 220958,
    "title": "Palau: Reise- und Sicherheitshinweise",
    "country_name": "Palau",
    "country_code": "PW",
    "iso3_country_code": "PLW",
    "last_modified_iso": "2025-08-08T17:28:00+00:00",
    "effective_iso": null,
    "warning": 0,
    "partial_warning": 0,
    "situation_warning": 0,
    "situation_part_warning": 0
  },
  {
    "content_id": 220400,
    "title": "Marshallinseln: Reise- und Sicherheitshinweise",
    "country_name": "Marshallinseln",
    "country_code": "MH",
    "iso3_country_code": "MHL",
    "last_modified_iso": "2025-08-08T16:18:55+00:00",
    "effective_iso": null,
    "warning": 0,
    "partial_warning": 0,
    "situation_warning": 0,
    "situation_part_warning": 0
  },
  {
    "content_id": 213758,
    "title": "Samoa: Reise- und Sicherheitshinweise",
    "country_name": "Samoa",
    "country_code": "WS",
    "iso3_country_code": "WSM",
    "last_modified_iso": "2025-08-20T12:28:02+00:00",
    "effective_iso": null,
    "warning": 0,
    "partial_warning": 0,
    "situation_warning": 0,
    "situation_part_warning": 0
  },
  {
    "content_id": 213790,
    "title": "Tonga: Reise- und Sicherheitshinweise",
    "country_name": "Tonga",
    "country_code": "TO",
    "iso3_country_code": "TON",
    "last_modified_iso": "2025-08-20T12:28:02+00:00",
    "effective_iso": null,
    "warning": 0,
    "partial_warning": 0,
    "situation_warning": 0,
    "situation_part_warning": 0
  },
  {
    "content_id": 220364,
    "title": "Kiribati: Reise- und Sicherheitshinweise",
    "country_name": "Kiribati",
    "country_code": "KI",
    "iso3_country_code": "KIR",
    "last_modified_iso": "2025-08-20T12:28:02+00:00",
    "effective_iso": null,
    "warning": 0,
    "partial_warning": 0,
    "situation_warning": 0,
    "situation_part_warning": 0
  },
  {
    "content_id": 226768,
    "title": "Äquatorialguinea: Reise- und Sicherheitshinweise",
    "country_name": "Äquatorialguinea",
    "country_code": "GQ",
    "iso3_country_code": "GNQ",
    "last_modified_iso": "2025-09-05T09:08:08+00:00",
    "effective_iso": null,
    "warning": 0,
    "partial_warning": 0,
    "situation_warning": 0,
    "situation_part_warning": 0
  },
  {
    "content_id": 200872,
    "title": "Macau: Reise- und Sicherheitshinweise",
    "country_name": "Macau*",
    "country_code": "MO",
    "iso3_country_code": "MAC",
    "last_modified_iso": "2025-09-25T07:49:47+00:00",
    "effective_iso": null,
    "warning": 0,
    "partial_warning": 0,
    "situation_warning": 0,
    "situation_part_warning": 0
  },
  {
    "content_id": 208542,
    "title": "Republik Kongo: Reise- und Sicherheitshinweise",
    "country_name": "Republik Kongo",
    "country_code": "CG",
    "iso3_country_code": "COG",
    "last_modified_iso": "2025-09-25T09:44:31+00:00",
    "effective_iso": null,
    "warning": 0,
    "partial_warning": 0,
    "situation_warning": 0,
    "situation_part_warning": 0
  },
  {
    "content_id": 220348,
    "title": "Guyana: Reise- und Sicherheitshinweise",
    "country_name": "Guyana",
    "country_code": "GY",
    "iso3_country_code": "GUY",
    "last_modified_iso": "2025-09-26T09:56:52+00:00",
    "effective_iso": null,
    "warning": 0,
    "partial_warning": 0,
    "situation_warning": 0,
    "situation_part_warning": 0
  },
  {
    "content_id": 220666,
    "title": "Tuvalu: Reise- und Sicherheitshinweise",
    "country_name": "Tuvalu",
    "country_code": "TV",
    "iso3_country_code": "TUV",
    "last_modified_iso": "2025-10-02T09:03:16+00:00",
    "effective_iso": null,
    "warning": 0,
    "partial_warning": 0,
    "situation_warning": 0,
    "situation_part_warning": 0
  },
  {
    "content_id": 220268,
    "title": "Bahamas: Reise- und Sicherheitshinweise",
    "country_name": "Bahamas",
    "country_code": "BS",
    "iso3_country_code": "BHS",
    "last_modified_iso": "2025-10-02T08:49:34+00:00",
    "effective_iso": null,
    "warning": 0,
    "partial_warning": 0,
    "situation_warning": 0,
    "situation_part_warning": 0
  },
  {
    "content_id": 220416,
    "title": "Nauru: Reise- und Sicherheitshinweise",
    "country_name": "Nauru",
    "country_code": "NR",
    "iso3_country_code": "NRU",
    "last_modified_iso": "2025-10-02T08:54:18+00:00",
    "effective_iso": null,
    "warning": 0,
    "partial_warning": 0,
    "situation_warning": 0,
    "situation_part_warning": 0
  },
  {
    "content_id": 226268,
    "title": "St. Vincent und die Grenadinen: Reise- und Sicherheitshinweise",
    "country_name": "St. Vincent und die Grenadinen",
    "country_code": "VC",
    "iso3_country_code": "VCT",
    "last_modified_iso": "2025-10-06T09:17:14+00:00",
    "effective_iso": null,
    "warning": 0,
    "partial_warning": 0,
    "situation_warning": 0,
    "situation_part_warning": 0
  },
  {
    "content_id": 210822,
    "title": "Rumänien: Reise- und Sicherheitshinweise",
    "country_name": "Rumänien",
    "country_code": "RO",
    "iso3_country_code": "ROU",
    "last_modified_iso": "2025-10-15T12:32:22+00:00",
    "effective_iso": null,
    "warning": 0,
    "partial_warning": 0,
    "situation_warning": 0,
    "situation_part_warning": 0
  },
  {
    "content_id": 207612,
    "title": "Republik Nordmazedonien: Reise- und Sicherheitshinweise",
    "country_name": "Nordmazedonien",
    "country_code": "MK",
    "iso3_country_code": "MKD",
    "last_modified_iso": "2025-10-13T08:48:30+00:00",
    "effective_iso": null,
    "warning": 0,
    "partial_warning": 0,
    "situation_warning": 0,
    "situation_part_warning": 0
  },
  {
    "content_id": 211624,
    "title": "Finnland: Reise- und Sicherheitshinweise",
    "country_name": "Finnland",
    "country_code": "FI",
    "iso3_country_code": "FIN",
    "last_modified_iso": "2025-10-14T12:42:51+00:00",
    "effective_iso": null,
    "warning": 0,
    "partial_warning": 0,
    "situation_warning": 0,
    "situation_part_warning": 0
  },
  {
    "content_id": 226808,
    "title": "Heiliger Stuhl/Vatikan: Reise- und Sicherheitshinweise",
    "country_name": "Heiliger Stuhl / Vatikan",
    "country_code": "VA",
    "iso3_country_code": "VAT",
    "last_modified_iso": "2025-10-14T12:46:01+00:00",
    "effective_iso": null,
    "warning": 0,
    "partial_warning": 0,
    "situation_warning": 0,
    "situation_part_warning": 0
  },
  {
    "content_id": 211188,
    "title": "Malta: Reise- und Sicherheitshinweise",
    "country_name": "Malta",
    "country_code": "MT",
    "iso3_country_code": "MLT",
    "last_modified_iso": "2025-10-14T12:59:51+00:00",
    "effective_iso": null,
    "warning": 0,
    "partial_warning": 0,
    "situation_warning": 0,
    "situation_part_warning": 0
  },
  {
    "content_id": 211256,
    "title": "Luxemburg: Reise- und Sicherheitshinweise",
    "country_name": "Luxemburg",
    "country_code": "LU",
    "iso3_country_code": "LUX",
    "last_modified_iso": "2025-10-14T12:59:34+00:00",
    "effective_iso": null,
    "warning": 0,
    "partial_warning": 0,
    "situation_warning": 0,
    "situation_part_warning": 0
  },
  {
    "content_id": 222960,
    "title": "Liechtenstein: Reise- und Sicherheitshinweise",
    "country_name": "Liechtenstein",
    "country_code": "LI",
    "iso3_country_code": "LIE",
    "last_modified_iso": "2025-10-14T12:59:00+00:00",
    "effective_iso": null,
    "warning": 0,
    "partial_warning": 0,
    "situation_warning": 0,
    "situation_part_warning": 0
  },
  {
    "content_id": 226868,
    "title": "Monaco: Reise- und Sicherheitshinweise",
    "country_name": "Monaco",
    "country_code": "MC",
    "iso3_country_code": "MCO",
    "last_modified_iso": "2025-10-14T13:00:12+00:00",
    "effective_iso": null,
    "warning": 0,
    "partial_warning": 0,
    "situation_warning": 0,
    "situation_part_warning": 0
  },
  {
    "content_id": 210072,
    "title": "Kroatien: Reise- und Sicherheitshinweise",
    "country_name": "Kroatien",
    "country_code": "HR",
    "iso3_country_code": "HRV",
    "last_modified_iso": "2025-10-14T12:58:27+00:00",
    "effective_iso": null,
    "warning": 0,
    "partial_warning": 0,
    "situation_warning": 0,
    "situation_part_warning": 0
  },
  {
    "content_id": 226626,
    "title": "Fidschi: Reise- und Sicherheitshinweise",
    "country_name": "Fidschi",
    "country_code": "FJ",
    "iso3_country_code": "FJI",
    "last_modified_iso": "2025-10-16T14:40:27+00:00",
    "effective_iso": null,
    "warning": 0,
    "partial_warning": 0,
    "situation_warning": 0,
    "situation_part_warning": 0
  },
  {
    "content_id": 200674,
    "title": "Lettland: Reise- und Sicherheitshinweise",
    "country_name": "Lettland",
    "country_code": "LV",
    "iso3_country_code": "LVA",
    "last_modified_iso": "2025-10-16T14:34:32+00:00",
    "effective_iso": null,
    "warning": 0,
    "partial_warning": 0,
    "situation_warning": 0,
    "situation_part_warning": 0
  },
  {
    "content_id": 206360,
    "title": "Slowakei: Reise- und Sicherheitshinweise",
    "country_name": "Slowakei",
    "country_code": "SK",
    "iso3_country_code": "SVK",
    "last_modified_iso": "2025-10-15T12:37:22+00:00",
    "effective_iso": null,
    "warning": 0,
    "partial_warning": 0,
    "situation_warning": 0,
    "situation_part_warning": 0
  },
  {
    "content_id": 200754,
    "title": "Estland: Reise- und Sicherheitshinweise",
    "country_name": "Estland",
    "country_code": "EE",
    "iso3_country_code": "EST",
    "last_modified_iso": "2025-10-17T16:05:11+00:00",
    "effective_iso": null,
    "warning": 0,
    "partial_warning": 0,
    "situation_warning": 0,
    "situation_part_warning": 0
  },
  {
    "content_id": 213624,
    "title": "Gambia: Reise- und Sicherheitshinweise",
    "country_name": "Gambia",
    "country_code": "GM",
    "iso3_country_code": "GMB",
    "last_modified_iso": "2025-11-03T10:56:51+00:00",
    "effective_iso": null,
    "warning": 0,
    "partial_warning": 0,
    "situation_warning": 0,
    "situation_part_warning": 0
  },
  {
    "content_id": 226974,
    "title": "Lesotho: Reise- und Sicherheitshinweise",
    "country_name": "Lesotho",
    "country_code": "LS",
    "iso3_country_code": "LSO",
    "last_modified_iso": "2025-11-03T14:20:08+00:00",
    "effective_iso": null,
    "warning": 0,
    "partial_warning": 0,
    "situation_warning": 0,
    "situation_part_warning": 0
  },
  {
    "content_id": 205048,
    "title": "Haiti: Reise- und Sicherheitshinweise",
    "country_name": "Haiti",
    "country_code": "HT",
    "iso3_country_code": "HTI",
    "last_modified_iso": "2025-10-27T09:44:05+00:00",
    "effective_iso": null,
    "warning": 1,
    "partial_warning": 0,
    "situation_warning": 0,
    "situation_part_warning": 0
  },
  {
    "content_id": 216330,
    "title": "Montenegro: Reise- und Sicherheitshinweise",
    "country_name": "Montenegro",
    "country_code": "ME",
    "iso3_country_code": "MNE",
    "last_modified_iso": "2025-10-02T08:53:54+00:00",
    "effective_iso": null,
    "warning": 0,
    "partial_warning": 0,
    "situation_warning": 0,
    "situation_part_warning": 0
  },
  {
    "content_id": 210644,
    "title": "Slowenien: Reise- und Sicherheitshinweise",
    "country_name": "Slowenien",
    "country_code": "SI",
    "iso3_country_code": "SVN",
    "last_modified_iso": "2025-11-19T16:53:16+00:00",
    "effective_iso": null,
    "warning": 0,
    "partial_warning": 0,
    "situation_warning": 0,
    "situation_part_warning": 0
  },
  {
    "content_id": 203500,
    "title": "Sierra Leone: Reise- und Sicherheitshinweise",
    "country_name": "Sierra Leone",
    "country_code": "SL",
    "iso3_country_code": "SLE",
    "last_modified_iso": "2025-11-11T15:48:34+00:00",
    "effective_iso": null,
    "warning": 0,
    "partial_warning": 0,
    "situation_warning": 0,
    "situation_part_warning": 0
  },
  {
    "content_id": 222378,
    "title": "Liberia: Reise- und Sicherheitshinweise",
    "country_name": "Liberia",
    "country_code": "LR",
    "iso3_country_code": "LBR",
    "last_modified_iso": "2025-11-11T15:51:46+00:00",
    "effective_iso": null,
    "warning": 0,
    "partial_warning": 0,
    "situation_warning": 0,
    "situation_part_warning": 0
  },
  {
    "content_id": 212168,
    "title": "Dschibuti: Reise- und Sicherheitshinweise",
    "country_name": "Dschibuti",
    "country_code": "DJ",
    "iso3_country_code": "DJI",
    "last_modified_iso": "2025-11-12T11:00:57+00:00",
    "effective_iso": null,
    "warning": 0,
    "partial_warning": 0,
    "situation_warning": 0,
    "situation_part_warning": 0
  },
  {
    "content_id": 219624,
    "title": "Libyen: Reise- und Sicherheitshinweise",
    "country_name": "Libyen",
    "country_code": "LY",
    "iso3_country_code": "LBY",
    "last_modified_iso": "2025-11-26T10:17:06+00:00",
    "effective_iso": null,
    "warning": 1,
    "partial_warning": 0,
    "situation_warning": 0,
    "situation_part_warning": 0
  },
  {
    "content_id": 213850,
    "title": "Togo: Reise- und Sicherheitshinweise",
    "country_name": "Togo",
    "country_code": "TG",
    "iso3_country_code": "TGO",
    "last_modified_iso": "2025-11-26T11:08:40+00:00",
    "effective_iso": null,
    "warning": 0,
    "partial_warning": 1,
    "situation_warning": 0,
    "situation_part_warning": 0
  },
  {
    "content_id": 244250,
    "title": "Südsudan: Reise- und Sicherheitshinweise",
    "country_name": "Südsudan",
    "country_code": "SS",
    "iso3_country_code": "SSD",
    "last_modified_iso": "2025-12-01T14:09:51+00:00",
    "effective_iso": null,
    "warning": 1,
    "partial_warning": 0,
    "situation_warning": 0,
    "situation_part_warning": 0
  },
  {
    "content_id": 226450,
    "title": "Zentralafrikanische Republik: Reise- und Sicherheitshinweise",
    "country_name": "Zentralafrikanische Republik",
    "country_code": "CF",
    "iso3_country_code": "CAF",
    "last_modified_iso": "2025-12-01T14:10:48+00:00",
    "effective_iso": null,
    "warning": 1,
    "partial_warning": 0,
    "situation_warning": 0,
    "situation_part_warning": 0
  },
  {
    "content_id": 226324,
    "title": "Gabun: Reise- und Sicherheitshinweise",
    "country_name": "Gabun",
    "country_code": "GA",
    "iso3_country_code": "GAB",
    "last_modified_iso": "2025-12-01T14:01:14+00:00",
    "effective_iso": null,
    "warning": 0,
    "partial_warning": 0,
    "situation_warning": 0,
    "situation_part_warning": 0
  },
  {
    "content_id": 209460,
    "title": "Côte d'Ivoire: Reise- und Sicherheitshinweise",
    "country_name": "Côte d'Ivoire",
    "country_code": "CI",
    "iso3_country_code": "CIV",
    "last_modified_iso": "2025-12-01T13:53:31+00:00",
    "effective_iso": null,
    "warning": 0,
    "partial_warning": 1,
    "situation_warning": 0,
    "situation_part_warning": 0
  },
  {
    "content_id": 221388,
    "title": "Timor-Leste: Reise- und Sicherheitshinweise",
    "country_name": "Timor-Leste",
    "country_code": "TL",
    "iso3_country_code": "TLS",
    "last_modified_iso": "2025-12-04T10:56:38+00:00",
    "effective_iso": null,
    "warning": 0,
    "partial_warning": 0,
    "situation_warning": 0,
    "situation_part_warning": 0
  },
  {
    "content_id": 200382,
    "title": "Belgien: Reise- und Sicherheitshinweise",
    "country_name": "Belgien",
    "country_code": "BE",
    "iso3_country_code": "BEL",
    "last_modified_iso": "2025-12-04T08:43:48+00:00",
    "effective_iso": null,
    "warning": 0,
    "partial_warning": 0,
    "situation_warning": 0,
    "situation_part_warning": 0
  },
  {
    "content_id": 200620,
    "title": "Litauen: Reise- und Sicherheitshinweise",
    "country_name": "Litauen",
    "country_code": "LT",
    "iso3_country_code": "LTU",
    "last_modified_iso": "2025-12-04T12:10:57+00:00",
    "effective_iso": null,
    "warning": 0,
    "partial_warning": 0,
    "situation_warning": 0,
    "situation_part_warning": 0
  },
  {
    "content_id": 220466,
    "title": "Trinidad und Tobago: Reise- und Sicherheitshinweise",
    "country_name": "Trinidad und Tobago",
    "country_code": "TT",
    "iso3_country_code": "TTO",
    "last_modified_iso": "2025-12-05T13:44:31+00:00",
    "effective_iso": null,
    "warning": 0,
    "partial_warning": 0,
    "situation_warning": 0,
    "situation_part_warning": 0
  },
  {
    "content_id": 201872,
    "title": "Armenien: Reise- und Sicherheitshinweise",
    "country_name": "Armenien",
    "country_code": "AM",
    "iso3_country_code": "ARM",
    "last_modified_iso": "2025-07-02T15:49:57+00:00",
    "effective_iso": null,
    "warning": 0,
    "partial_warning": 1,
    "situation_warning": 0,
    "situation_part_warning": 0
  },
  {
    "content_id": 208948,
    "title": "Simbabwe: Reise- und Sicherheitshinweise",
    "country_name": "Simbabwe",
    "country_code": "ZW",
    "iso3_country_code": "ZWE",
    "last_modified_iso": "2025-11-11T15:45:20+00:00",
    "effective_iso": null,
    "warning": 0,
    "partial_warning": 0,
    "situation_warning": 0,
    "situation_part_warning": 0
  },
  {
    "content_id": 208606,
    "title": "Sambia: Reise- und Sicherheitshinweise",
    "country_name": "Sambia",
    "country_code": "ZM",
    "iso3_country_code": "ZMB",
    "last_modified_iso": "2025-12-11T15:58:29+00:00",
    "effective_iso": null,
    "warning": 0,
    "partial_warning": 0,
    "situation_warning": 0,
    "situation_part_warning": 0
  },
  {
    "content_id": 224898,
    "title": "Andorra: Reise- und Sicherheitshinweise",
    "country_name": "Andorra",
    "country_code": "AD",
    "iso3_country_code": "AND",
    "last_modified_iso": "2025-12-11T09:52:25+00:00",
    "effective_iso": null,
    "warning": 0,
    "partial_warning": 0,
    "situation_warning": 0,
    "situation_part_warning": 0
  },
  {
    "content_id": 211834,
    "title": "Bulgarien: Reise- und Sicherheitshinweise",
    "country_name": "Bulgarien",
    "country_code": "BG",
    "iso3_country_code": "BGR",
    "last_modified_iso": "2026-01-06T13:59:42+00:00",
    "effective_iso": null,
    "warning": 0,
    "partial_warning": 0,
    "situation_warning": 0,
    "situation_part_warning": 0
  },
  {
    "content_id": 220678,
    "title": "Föderierte Staaten von Mikronesien: Reise- und Sicherheitshinweise",
    "country_name": "Mikronesien",
    "country_code": "FM",
    "iso3_country_code": "FSM",
    "last_modified_iso": "2026-01-06T14:24:24+00:00",
    "effective_iso": null,
    "warning": 0,
    "partial_warning": 0,
    "situation_warning": 0,
    "situation_part_warning": 0
  },
  {
    "content_id": 208874,
    "title": "Kamerun: Reise- und Sicherheitshinweise",
    "country_name": "Kamerun",
    "country_code": "CM",
    "iso3_country_code": "CMR",
    "last_modified_iso": "2026-01-07T10:34:46+00:00",
    "effective_iso": null,
    "warning": 0,
    "partial_warning": 1,
    "situation_warning": 0,
    "situation_part_warning": 0
  },
  {
    "content_id": 210332,
    "title": "Ungarn: Reise- und Sicherheitshinweise",
    "country_name": "Ungarn",
    "country_code": "HU",
    "iso3_country_code": "HUN",
    "last_modified_iso": "2026-01-07T13:59:31+00:00",
    "effective_iso": null,
    "warning": 0,
    "partial_warning": 0,
    "situation_warning": 0,
    "situation_part_warning": 0
  },
  {
    "content_id": 220284,
    "title": "Belize: Reise- und Sicherheitshinweise",
    "country_name": "Belize",
    "country_code": "BZ",
    "iso3_country_code": "BLZ",
    "last_modified_iso": "2025-10-06T07:24:43+00:00",
    "effective_iso": null,
    "warning": 0,
    "partial_warning": 0,
    "situation_warning": 0,
    "situation_part_warning": 0
  },
  {
    "content_id": 210456,
    "title": "Tschechische Republik: Reise- und Sicherheitshinweise",
    "country_name": "Tschechien",
    "country_code": "CZ",
    "iso3_country_code": "CZE",
    "last_modified_iso": "2025-12-04T13:47:27+00:00",
    "effective_iso": null,
    "warning": 0,
    "partial_warning": 0,
    "situation_warning": 0,
    "situation_part_warning": 0
  },
  {
    "content_id": 227014,
    "title": "San Marino: Reise- und Sicherheitshinweise",
    "country_name": "San Marino",
    "country_code": "SM",
    "iso3_country_code": "SMR",
    "last_modified_iso": "2025-12-19T10:37:17+00:00",
    "effective_iso": null,
    "warning": 0,
    "partial_warning": 0,
    "situation_warning": 0,
    "situation_part_warning": 0
  },
  {
    "content_id": 227042,
    "title": "Antigua und Barbuda: Reise- und Sicherheitshinweise",
    "country_name": "Antigua und Barbuda",
    "country_code": "AG",
    "iso3_country_code": "ATG",
    "last_modified_iso": "2025-12-19T14:51:13+00:00",
    "effective_iso": null,
    "warning": 0,
    "partial_warning": 0,
    "situation_warning": 0,
    "situation_part_warning": 0
  },
  {
    "content_id": 212336,
    "title": "Burkina Faso: Reise- und Sicherheitshinweise",
    "country_name": "Burkina Faso",
    "country_code": "BF",
    "iso3_country_code": "BFA",
    "last_modified_iso": "2025-12-18T12:37:57+00:00",
    "effective_iso": null,
    "warning": 0,
    "partial_warning": 1,
    "situation_warning": 0,
    "situation_part_warning": 0
  },
  {
    "content_id": 223400,
    "title": "Island: Reise- und Sicherheitshinweise",
    "country_name": "Island",
    "country_code": "IS",
    "iso3_country_code": "ISL",
    "last_modified_iso": "2025-12-18T09:34:11+00:00",
    "effective_iso": null,
    "warning": 0,
    "partial_warning": 0,
    "situation_warning": 0,
    "situation_part_warning": 0
  },
  {
    "content_id": 222614,
    "title": "Burundi: Reise- und Sicherheitshinweise",
    "country_name": "Burundi",
    "country_code": "BI",
    "iso3_country_code": "BDI",
    "last_modified_iso": "2025-12-18T13:33:13+00:00",
    "effective_iso": null,
    "warning": 0,
    "partial_warning": 0,
    "situation_warning": 0,
    "situation_part_warning": 0
  },
  {
    "content_id": 221782,
    "title": "Mosambik: Reise- und Sicherheitshinweise",
    "country_name": "Mosambik",
    "country_code": "MZ",
    "iso3_country_code": "MOZ",
    "last_modified_iso": "2025-11-20T13:43:17+00:00",
    "effective_iso": null,
    "warning": 0,
    "partial_warning": 1,
    "situation_warning": 0,
    "situation_part_warning": 0
  },
  {
    "content_id": 203266,
    "title": "Sudan: Reise- und Sicherheitshinweise",
    "country_name": "Sudan",
    "country_code": "SD",
    "iso3_country_code": "SDN",
    "last_modified_iso": "2024-11-20T10:36:18+00:00",
    "effective_iso": null,
    "warning": 1,
    "partial_warning": 0,
    "situation_warning": 0,
    "situation_part_warning": 0
  },
  {
    "content_id": 203202,
    "title": "Demokratische Republik Kongo: Reise- und Sicherheitshinweise",
    "country_name": "Demokratische Republik Kongo",
    "country_code": "CD",
    "iso3_country_code": "COD",
    "last_modified_iso": "2025-12-11T14:30:20+00:00",
    "effective_iso": null,
    "warning": 0,
    "partial_warning": 1,
    "situation_warning": 0,
    "situation_part_warning": 0
  },
  {
    "content_id": 206098,
    "title": "Guinea: Reise- und Sicherheitshinweise",
    "country_name": "Guinea",
    "country_code": "GN",
    "iso3_country_code": "GIN",
    "last_modified_iso": "2025-12-29T09:10:13+00:00",
    "effective_iso": null,
    "warning": 0,
    "partial_warning": 0,
    "situation_warning": 0,
    "situation_part_warning": 0
  },
  {
    "content_id": 221078,
    "title": "Honduras: Reise- und Sicherheitshinweise",
    "country_name": "Honduras",
    "country_code": "HN",
    "iso3_country_code": "HND",
    "last_modified_iso": "2025-12-29T15:54:59+00:00",
    "effective_iso": null,
    "warning": 0,
    "partial_warning": 0,
    "situation_warning": 0,
    "situation_part_warning": 0
  },
  {
    "content_id": 207442,
    "title": "Kosovo: Reise- und Sicherheitshinweise",
    "country_name": "Kosovo",
    "country_code": "XK",
    "iso3_country_code": "XKX",
    "last_modified_iso": "2025-07-31T16:16:15+00:00",
    "effective_iso": null,
    "warning": 0,
    "partial_warning": 0,
    "situation_warning": 0,
    "situation_part_warning": 0
  },
  {
    "content_id": 208258,
    "title": "Mali: Reise- und Sicherheitshinweise",
    "country_name": "Mali",
    "country_code": "ML",
    "iso3_country_code": "MLI",
    "last_modified_iso": "2025-12-30T11:10:09+00:00",
    "effective_iso": null,
    "warning": 1,
    "partial_warning": 0,
    "situation_warning": 0,
    "situation_part_warning": 0
  },
  {
    "content_id": 225774,
    "title": "Tschad: Reise- und Sicherheitshinweise",
    "country_name": "Tschad",
    "country_code": "TD",
    "iso3_country_code": "TCD",
    "last_modified_iso": "2025-12-30T11:26:04+00:00",
    "effective_iso": null,
    "warning": 0,
    "partial_warning": 1,
    "situation_warning": 0,
    "situation_part_warning": 0
  },
  {
    "content_id": 219190,
    "title": "Mauretanien: Reise- und Sicherheitshinweise",
    "country_name": "Mauretanien",
    "country_code": "MR",
    "iso3_country_code": "MRT",
    "last_modified_iso": "2025-12-30T11:12:35+00:00",
    "effective_iso": null,
    "warning": 0,
    "partial_warning": 1,
    "situation_warning": 0,
    "situation_part_warning": 0
  },
  {
    "content_id": 226384,
    "title": "Niger: Reise- und Sicherheitshinweise",
    "country_name": "Niger",
    "country_code": "NE",
    "iso3_country_code": "NER",
    "last_modified_iso": "2025-12-30T11:21:14+00:00",
    "effective_iso": null,
    "warning": 1,
    "partial_warning": 0,
    "situation_warning": 0,
    "situation_part_warning": 0
  },
  {
    "content_id": 207502,
    "title": "Serbien: Reise- und Sicherheitshinweise",
    "country_name": "Serbien",
    "country_code": "RS",
    "iso3_country_code": "SRB",
    "last_modified_iso": "2025-09-25T10:06:57+00:00",
    "effective_iso": null,
    "warning": 0,
    "partial_warning": 0,
    "situation_warning": 0,
    "situation_part_warning": 0
  },
  {
    "content_id": 219044,
    "title": "Algerien: Reise- und Sicherheitshinweise",
    "country_name": "Algerien",
    "country_code": "DZ",
    "iso3_country_code": "DZA",
    "last_modified_iso": "2025-11-12T10:49:35+00:00",
    "effective_iso": null,
    "warning": 0,
    "partial_warning": 1,
    "situation_warning": 0,
    "situation_part_warning": 0
  },
  {
    "content_id": 207694,
    "title": "Bosnien und Herzegowina: Reise- und Sicherheitshinweise",
    "country_name": "Bosnien und Herzegowina",
    "country_code": "BA",
    "iso3_country_code": "BIH",
    "last_modified_iso": "2025-06-06T13:00:04+00:00",
    "effective_iso": null,
    "warning": 0,
    "partial_warning": 0,
    "situation_warning": 0,
    "situation_part_warning": 0
  },
  {
    "content_id": 224526,
    "title": "Brunei Darussalam: Reise- und Sicherheitshinweise",
    "country_name": "Brunei Darussalam",
    "country_code": "BN",
    "iso3_country_code": "BRN",
    "last_modified_iso": "2026-01-05T10:35:37+00:00",
    "effective_iso": null,
    "warning": 0,
    "partial_warning": 0,
    "situation_warning": 0,
    "situation_part_warning": 0
  },
  {
    "content_id": 210258,
    "title": "Zypern: Reise- und Sicherheitshinweise",
    "country_name": "Zypern",
    "country_code": "CY",
    "iso3_country_code": "CYP",
    "last_modified_iso": "2026-01-05T10:20:28+00:00",
    "effective_iso": null,
    "warning": 0,
    "partial_warning": 0,
    "situation_warning": 0,
    "situation_part_warning": 0
  },
  {
    "content_id": 212100,
    "title": "Myanmar: Reise- und Sicherheitshinweise",
    "country_name": "Myanmar",
    "country_code": "MM",
    "iso3_country_code": "MMR",
    "last_modified_iso": "2026-01-05T11:03:18+00:00",
    "effective_iso": null,
    "warning": 1,
    "partial_warning": 0,
    "situation_warning": 0,
    "situation_part_warning": 0
  },
  {
    "content_id": 220698,
    "title": "Papua-Neuguinea: Reise- und Sicherheitshinweise",
    "country_name": "Papua-Neuguinea",
    "country_code": "PG",
    "iso3_country_code": "PNG",
    "last_modified_iso": "2026-01-05T11:09:51+00:00",
    "effective_iso": null,
    "warning": 0,
    "partial_warning": 0,
    "situation_warning": 0,
    "situation_part_warning": 0
  },
  {
    "content_id": 220498,
    "title": "Vanuatu: Reise- und Sicherheitshinweise",
    "country_name": "Vanuatu",
    "country_code": "VU",
    "iso3_country_code": "VUT",
    "last_modified_iso": "2026-01-05T11:31:24+00:00",
    "effective_iso": null,
    "warning": 0,
    "partial_warning": 0,
    "situation_warning": 0,
    "situation_part_warning": 0
  },
  {
    "content_id": 206292,
    "title": "Bangladesch: Reise- und Sicherheitshinweise",
    "country_name": "Bangladesch",
    "country_code": "BD",
    "iso3_country_code": "BGD",
    "last_modified_iso": "2026-01-05T09:16:27+00:00",
    "effective_iso": null,
    "warning": 0,
    "partial_warning": 0,
    "situation_warning": 0,
    "situation_part_warning": 0
  },
  {
    "content_id": 208984,
    "title": "Benin: Reise- und Sicherheitshinweise",
    "country_name": "Benin",
    "country_code": "BJ",
    "iso3_country_code": "BEN",
    "last_modified_iso": "2026-01-05T16:06:08+00:00",
    "effective_iso": null,
    "warning": 0,
    "partial_warning": 1,
    "situation_warning": 0,
    "situation_part_warning": 0
  },
  {
    "content_id": 201904,
    "title": "Belarus: Reise- und Sicherheitshinweise",
    "country_name": "Belarus",
    "country_code": "BY",
    "iso3_country_code": "BLR",
    "last_modified_iso": "2026-01-09T14:43:25+00:00",
    "effective_iso": null,
    "warning": 1,
    "partial_warning": 0,
    "situation_warning": 0,
    "situation_part_warning": 0
  },
  {
    "content_id": 210900,
    "title": "Portugal: Reise- und Sicherheitshinweise",
    "country_name": "Portugal",
    "country_code": "PT",
    "iso3_country_code": "PRT",
    "last_modified_iso": "2025-12-09T15:25:29+00:00",
    "effective_iso": null,
    "warning": 0,
    "partial_warning": 0,
    "situation_warning": 0,
    "situation_part_warning": 0
  },
  {
    "content_id": 210708,
    "title": "Schweden: Reise- und Sicherheitshinweise",
    "country_name": "Schweden",
    "country_code": "SE",
    "iso3_country_code": "SWE",
    "last_modified_iso": "2025-10-15T12:35:32+00:00",
    "effective_iso": null,
    "warning": 0,
    "partial_warning": 0,
    "situation_warning": 0,
    "situation_part_warning": 0
  },
  {
    "content_id": 212026,
    "title": "Ruanda: Reise- und Sicherheitshinweise",
    "country_name": "Ruanda",
    "country_code": "RW",
    "iso3_country_code": "RWA",
    "last_modified_iso": "2025-12-01T14:07:59+00:00",
    "effective_iso": null,
    "warning": 0,
    "partial_warning": 0,
    "situation_warning": 0,
    "situation_part_warning": 0
  },
  {
    "content_id": 203372,
    "title": "Ghana: Reise- und Sicherheitshinweise",
    "country_name": "Ghana",
    "country_code": "GH",
    "iso3_country_code": "GHA",
    "last_modified_iso": "2025-09-01T09:37:02+00:00",
    "effective_iso": null,
    "warning": 0,
    "partial_warning": 1,
    "situation_warning": 0,
    "situation_part_warning": 0
  },
  {
    "content_id": 226176,
    "title": "Eritrea: Reise- und Sicherheitshinweise",
    "country_name": "Eritrea",
    "country_code": "ER",
    "iso3_country_code": "ERI",
    "last_modified_iso": "2026-01-08T11:41:30+00:00",
    "effective_iso": null,
    "warning": 0,
    "partial_warning": 1,
    "situation_warning": 0,
    "situation_part_warning": 0
  },
  {
    "content_id": 203132,
    "title": "Somalia: Reise- und Sicherheitshinweise",
    "country_name": "Somalia",
    "country_code": "SO",
    "iso3_country_code": "SOM",
    "last_modified_iso": "2025-11-26T11:03:37+00:00",
    "effective_iso": null,
    "warning": 1,
    "partial_warning": 0,
    "situation_warning": 0,
    "situation_part_warning": 0
  },
  {
    "content_id": 208190,
    "title": "Senegal: Reise- und Sicherheitshinweise",
    "country_name": "Senegal",
    "country_code": "SN",
    "iso3_country_code": "SEN",
    "last_modified_iso": "2025-12-30T11:33:21+00:00",
    "effective_iso": null,
    "warning": 0,
    "partial_warning": 0,
    "situation_warning": 0,
    "situation_part_warning": 0
  },
  {
    "content_id": 201138,
    "title": "Uruguay: Reise- und Sicherheitshinweise",
    "country_name": "Uruguay",
    "country_code": "UY",
    "iso3_country_code": "URY",
    "last_modified_iso": "2025-11-11T15:15:54+00:00",
    "effective_iso": null,
    "warning": 0,
    "partial_warning": 0,
    "situation_warning": 0,
    "situation_part_warning": 0
  },
  {
    "content_id": 208752,
    "title": "Uganda: Reise- und Sicherheitshinweise",
    "country_name": "Uganda",
    "country_code": "UG",
    "iso3_country_code": "UGA",
    "last_modified_iso": "2026-01-14T10:05:01+00:00",
    "effective_iso": null,
    "warning": 0,
    "partial_warning": 0,
    "situation_warning": 0,
    "situation_part_warning": 0
  },
  {
    "content_id": 220382,
    "title": "Malediven: Reise- und Sicherheitshinweise",
    "country_name": "Malediven",
    "country_code": "MV",
    "iso3_country_code": "MDV",
    "last_modified_iso": "2025-12-22T09:33:53+00:00",
    "effective_iso": null,
    "warning": 0,
    "partial_warning": 0,
    "situation_warning": 0,
    "situation_part_warning": 0
  },
  {
    "content_id": 204278,
    "title": "Syrien: Reise- und Sicherheitshinweise",
    "country_name": "Syrien",
    "country_code": "SY",
    "iso3_country_code": "SYR",
    "last_modified_iso": "2026-01-14T16:00:25+00:00",
    "effective_iso": null,
    "warning": 1,
    "partial_warning": 0,
    "situation_warning": 0,
    "situation_part_warning": 0
  },
  {
    "content_id": 205788,
    "title": "Nigeria: Reise- und Sicherheitshinweise",
    "country_name": "Nigeria",
    "country_code": "NG",
    "iso3_country_code": "NGA",
    "last_modified_iso": "2026-01-13T14:13:01+00:00",
    "effective_iso": null,
    "warning": 0,
    "partial_warning": 1,
    "situation_warning": 0,
    "situation_part_warning": 0
  },
  {
    "content_id": 201932,
    "title": "Moldau, Republik: Reise- und Sicherheitshinweise",
    "country_name": "Republik Moldau",
    "country_code": "MD",
    "iso3_country_code": "MDA",
    "last_modified_iso": "2026-01-13T15:39:41+00:00",
    "effective_iso": null,
    "warning": 0,
    "partial_warning": 0,
    "situation_warning": 0,
    "situation_part_warning": 0
  },
  {
    "content_id": 206756,
    "title": "Tadschikistan: Reise- und Sicherheitshinweise",
    "country_name": "Tadschikistan",
    "country_code": "TJ",
    "iso3_country_code": "TJK",
    "last_modified_iso": "2026-01-14T10:10:42+00:00",
    "effective_iso": null,
    "warning": 0,
    "partial_warning": 0,
    "situation_warning": 0,
    "situation_part_warning": 0
  },
  {
    "content_id": 226596,
    "title": "St. Kitts und Nevis: Reise- und Sicherheitshinweise",
    "country_name": "St. Kitts und Nevis",
    "country_code": "KN",
    "iso3_country_code": "KNA",
    "last_modified_iso": "2026-01-14T10:38:51+00:00",
    "effective_iso": null,
    "warning": 0,
    "partial_warning": 0,
    "situation_warning": 0,
    "situation_part_warning": 0
  },
  {
    "content_id": 201888,
    "title": "Aserbaidschan: Reise- und Sicherheitshinweise",
    "country_name": "Aserbaidschan",
    "country_code": "AZ",
    "iso3_country_code": "AZE",
    "last_modified_iso": "2025-07-08T13:13:12+00:00",
    "effective_iso": null,
    "warning": 0,
    "partial_warning": 1,
    "situation_warning": 0,
    "situation_part_warning": 0
  },
  {
    "content_id": 202260,
    "title": "Jemen: Reise- und Sicherheitshinweise",
    "country_name": "Jemen",
    "country_code": "YE",
    "iso3_country_code": "YEM",
    "last_modified_iso": "2026-01-14T16:00:01+00:00",
    "effective_iso": null,
    "warning": 1,
    "partial_warning": 0,
    "situation_warning": 0,
    "situation_part_warning": 0
  },
  {
    "content_id": 204112,
    "title": "Bahrain: Reise- und Sicherheitshinweise",
    "country_name": "Bahrain",
    "country_code": "BH",
    "iso3_country_code": "BHR",
    "last_modified_iso": "2026-01-14T15:35:07+00:00",
    "effective_iso": null,
    "warning": 0,
    "partial_warning": 0,
    "situation_warning": 0,
    "situation_part_warning": 0
  },
  {
    "content_id": 204130,
    "title": "Kuwait: Reise- und Sicherheitshinweise",
    "country_name": "Kuwait",
    "country_code": "KW",
    "iso3_country_code": "KWT",
    "last_modified_iso": "2026-01-14T15:39:46+00:00",
    "effective_iso": null,
    "warning": 0,
    "partial_warning": 0,
    "situation_warning": 0,
    "situation_part_warning": 0
  },
  {
    "content_id": 210962,
    "title": "Österreich: Reise- und Sicherheitshinweise",
    "country_name": "Österreich",
    "country_code": "AT",
    "iso3_country_code": "AUT",
    "last_modified_iso": "2025-10-14T13:01:07+00:00",
    "effective_iso": null,
    "warning": 0,
    "partial_warning": 0,
    "situation_warning": 0,
    "situation_part_warning": 0
  },
  {
    "content_id": 221864,
    "title": "El Salvador: Reise- und Sicherheitshinweise",
    "country_name": "El Salvador",
    "country_code": "SV",
    "iso3_country_code": "SLV",
    "last_modified_iso": "2025-09-23T14:52:27+00:00",
    "effective_iso": null,
    "warning": 0,
    "partial_warning": 0,
    "situation_warning": 0,
    "situation_part_warning": 0
  },
  {
    "content_id": 209504,
    "title": "Äthiopien: Reise- und Sicherheitshinweise",
    "country_name": "Äthiopien",
    "country_code": "ET",
    "iso3_country_code": "ETH",
    "last_modified_iso": "2025-12-18T13:12:45+00:00",
    "effective_iso": null,
    "warning": 0,
    "partial_warning": 1,
    "situation_warning": 0,
    "situation_part_warning": 0
  },
  {
    "content_id": 204692,
    "title": "Afghanistan: Reise- und Sicherheitshinweise",
    "country_name": "Afghanistan",
    "country_code": "AF",
    "iso3_country_code": "AFG",
    "last_modified_iso": "2025-10-08T16:30:32+00:00",
    "effective_iso": null,
    "warning": 1,
    "partial_warning": 0,
    "situation_warning": 0,
    "situation_part_warning": 0
  },
  {
    "content_id": 208824,
    "title": "Cabo Verde: Reise- und Sicherheitshinweise",
    "country_name": "Cabo Verde",
    "country_code": "CV",
    "iso3_country_code": "CPV",
    "last_modified_iso": "2025-12-18T13:37:41+00:00",
    "effective_iso": null,
    "warning": 0,
    "partial_warning": 0,
    "situation_warning": 0,
    "situation_part_warning": 0
  },
  {
    "content_id": 213032,
    "title": "Japan: Reise- und Sicherheitshinweise",
    "country_name": "Japan",
    "country_code": "JP",
    "iso3_country_code": "JPN",
    "last_modified_iso": "2025-11-03T13:48:19+00:00",
    "effective_iso": null,
    "warning": 0,
    "partial_warning": 1,
    "situation_warning": 0,
    "situation_part_warning": 0
  },
  {
    "content_id": 211322,
    "title": "Italien: Reise- und Sicherheitshinweise",
    "country_name": "Italien",
    "country_code": "IT",
    "iso3_country_code": "ITA",
    "last_modified_iso": "2025-10-27T14:15:03+00:00",
    "effective_iso": null,
    "warning": 0,
    "partial_warning": 0,
    "situation_warning": 0,
    "situation_part_warning": 0
  },
  {
    "content_id": 209524,
    "title": "Frankreich: Reise- und Sicherheitshinweise",
    "country_name": "Frankreich",
    "country_code": "FR",
    "iso3_country_code": "FRA",
    "last_modified_iso": "2025-11-18T10:57:40+00:00",
    "effective_iso": null,
    "warning": 0,
    "partial_warning": 0,
    "situation_warning": 0,
    "situation_part_warning": 0
  },
  {
    "content_id": 201048,
    "title": "Laos: Reise- und Sicherheitshinweise",
    "country_name": "Laos",
    "country_code": "LA",
    "iso3_country_code": "LAO",
    "last_modified_iso": "2026-01-05T10:50:51+00:00",
    "effective_iso": null,
    "warning": 0,
    "partial_warning": 0,
    "situation_warning": 0,
    "situation_part_warning": 0
  },
  {
    "content_id": 200466,
    "title": "China: Reise- und Sicherheitshinweise",
    "country_name": "China",
    "country_code": "CN",
    "iso3_country_code": "CHN",
    "last_modified_iso": "2025-11-04T10:59:59+00:00",
    "effective_iso": null,
    "warning": 0,
    "partial_warning": 0,
    "situation_warning": 0,
    "situation_part_warning": 0
  },
  {
    "content_id": 212622,
    "title": "Ägypten: Reise- und Sicherheitshinweise",
    "country_name": "Ägypten",
    "country_code": "EG",
    "iso3_country_code": "EGY",
    "last_modified_iso": "2025-11-25T10:21:30+00:00",
    "effective_iso": null,
    "warning": 0,
    "partial_warning": 1,
    "situation_warning": 0,
    "situation_part_warning": 0
  },
  {
    "content_id": 199124,
    "title": "Polen: Reise- und Sicherheitshinweise",
    "country_name": "Polen",
    "country_code": "PL",
    "iso3_country_code": "POL",
    "last_modified_iso": "2026-01-15T13:57:41+00:00",
    "effective_iso": null,
    "warning": 0,
    "partial_warning": 0,
    "situation_warning": 0,
    "situation_part_warning": 0
  },
  {
    "content_id": 201946,
    "title": "Ukraine: Reise- und Sicherheitshinweise",
    "country_name": "Ukraine",
    "country_code": "UA",
    "iso3_country_code": "UKR",
    "last_modified_iso": "2025-12-23T13:05:41+00:00",
    "effective_iso": null,
    "warning": 1,
    "partial_warning": 0,
    "situation_warning": 0,
    "situation_part_warning": 0
  },
  {
    "content_id": 216104,
    "title": "Demokratische Volksrepublik Korea (Nordkorea): Reise- und Sicherheitshinweise",
    "country_name": "Demokratische Volksrepublik Korea (Nordkorea)",
    "country_code": "KP",
    "iso3_country_code": "PRK",
    "last_modified_iso": "2024-11-28T10:56:46+00:00",
    "effective_iso": null,
    "warning": 0,
    "partial_warning": 0,
    "situation_warning": 0,
    "situation_part_warning": 0
  },
  {
    "content_id": 204048,
    "title": "Libanon: Reise- und Sicherheitshinweise",
    "country_name": "Libanon",
    "country_code": "LB",
    "iso3_country_code": "LBN",
    "last_modified_iso": "2025-12-22T09:20:49+00:00",
    "effective_iso": null,
    "warning": 0,
    "partial_warning": 1,
    "situation_warning": 0,
    "situation_part_warning": 0
  },
  {
    "content_id": 202396,
    "title": "Iran: Reise- und Sicherheitshinweise",
    "country_name": "Iran",
    "country_code": "IR",
    "iso3_country_code": "IRN",
    "last_modified_iso": "2026-01-14T18:24:48+00:00",
    "effective_iso": null,
    "warning": 1,
    "partial_warning": 0,
    "situation_warning": 0,
    "situation_part_warning": 0
  },
  {
    "content_id": 202738,
    "title": "Irak: Reise- und Sicherheitshinweise",
    "country_name": "Irak",
    "country_code": "IQ",
    "iso3_country_code": "IRQ",
    "last_modified_iso": "2026-01-14T15:59:43+00:00",
    "effective_iso": null,
    "warning": 0,
    "partial_warning": 1,
    "situation_warning": 0,
    "situation_part_warning": 0
  },
  {
    "content_id": 205998,
    "title": "Indien: Reise- und Sicherheitshinweise",
    "country_name": "Indien",
    "country_code": "IN",
    "iso3_country_code": "IND",
    "last_modified_iso": "2025-12-04T11:45:54+00:00",
    "effective_iso": null,
    "warning": 0,
    "partial_warning": 1,
    "situation_warning": 0,
    "situation_part_warning": 0
  },
  {
    "content_id": 212396,
    "title": "Indonesien: Reise- und Sicherheitshinweise",
    "country_name": "Indonesien",
    "country_code": "ID",
    "iso3_country_code": "IDN",
    "last_modified_iso": "2026-01-06T14:39:48+00:00",
    "effective_iso": null,
    "warning": 0,
    "partial_warning": 0,
    "situation_warning": 0,
    "situation_part_warning": 0
  },
  {
    "content_id": 223232,
    "title": "Ecuador: Reise- und Sicherheitshinweise",
    "country_name": "Ecuador",
    "country_code": "EC",
    "iso3_country_code": "ECU",
    "last_modified_iso": "2025-12-30T20:03:50+00:00",
    "effective_iso": null,
    "warning": 0,
    "partial_warning": 0,
    "situation_warning": 0,
    "situation_part_warning": 0
  },
  {
    "content_id": 206408,
    "title": "Vereinigtes Königreich: Reise- und Sicherheitshinweise",
    "country_name": "Vereinigtes Königreich",
    "country_code": "GB",
    "iso3_country_code": "GBR",
    "last_modified_iso": "2026-01-13T15:40:55+00:00",
    "effective_iso": null,
    "warning": 0,
    "partial_warning": 0,
    "situation_warning": 0,
    "situation_part_warning": 0
  },
  {
    "content_id": 200854,
    "title": "Hongkong: Reise- und Sicherheitshinweise",
    "country_name": "Hongkong*",
    "country_code": "HK",
    "iso3_country_code": "HKG",
    "last_modified_iso": "2025-10-13T09:31:26+00:00",
    "effective_iso": null,
    "warning": 0,
    "partial_warning": 0,
    "situation_warning": 0,
    "situation_part_warning": 0
  },
  {
    "content_id": 201918,
    "title": "Georgien: Reise- und Sicherheitshinweise",
    "country_name": "Georgien",
    "country_code": "GE",
    "iso3_country_code": "GEO",
    "last_modified_iso": "2025-12-30T09:56:46+00:00",
    "effective_iso": null,
    "warning": 0,
    "partial_warning": 0,
    "situation_warning": 0,
    "situation_part_warning": 0
  },
  {
    "content_id": 221882,
    "title": "Guatemala: Reise- und Sicherheitshinweise",
    "country_name": "Guatemala",
    "country_code": "GT",
    "iso3_country_code": "GTM",
    "last_modified_iso": "2025-11-11T08:55:38+00:00",
    "effective_iso": null,
    "warning": 0,
    "partial_warning": 0,
    "situation_warning": 0,
    "situation_part_warning": 0
  },
  {
    "content_id": 211534,
    "title": "Griechenland: Reise- und Sicherheitshinweise",
    "country_name": "Griechenland",
    "country_code": "GR",
    "iso3_country_code": "GRC",
    "last_modified_iso": "2025-12-09T15:13:59+00:00",
    "effective_iso": null,
    "warning": 0,
    "partial_warning": 0,
    "situation_warning": 0,
    "situation_part_warning": 0
  },
  {
    "content_id": 202332,
    "title": "Vereinigte Arabische Emirate: Reise- und Sicherheitshinweise",
    "country_name": "Vereinigte Arabische Emirate",
    "country_code": "AE",
    "iso3_country_code": "ARE",
    "last_modified_iso": "2026-01-14T15:44:03+00:00",
    "effective_iso": null,
    "warning": 0,
    "partial_warning": 0,
    "situation_warning": 0,
    "situation_part_warning": 0
  },
  {
    "content_id": 212254,
    "title": "Sri Lanka: Reise- und Sicherheitshinweise",
    "country_name": "Sri Lanka",
    "country_code": "LK",
    "iso3_country_code": "LKA",
    "last_modified_iso": "2025-12-01T09:32:10+00:00",
    "effective_iso": null,
    "warning": 0,
    "partial_warning": 0,
    "situation_warning": 0,
    "situation_part_warning": 0
  },
  {
    "content_id": 206208,
    "title": "Schweiz: Reise- und Sicherheitshinweise",
    "country_name": "Schweiz",
    "country_code": "CH",
    "iso3_country_code": "CHE",
    "last_modified_iso": "2025-10-15T12:36:09+00:00",
    "effective_iso": null,
    "warning": 0,
    "partial_warning": 0,
    "situation_warning": 0,
    "situation_part_warning": 0
  },
  {
    "content_id": 206790,
    "title": "Usbekistan: Reise- und Sicherheitshinweise",
    "country_name": "Usbekistan",
    "country_code": "UZ",
    "iso3_country_code": "UZB",
    "last_modified_iso": "2025-07-02T14:03:46+00:00",
    "effective_iso": null,
    "warning": 0,
    "partial_warning": 0,
    "situation_warning": 0,
    "situation_part_warning": 0
  },
  {
    "content_id": 225412,
    "title": "Singapur: Reise- und Sicherheitshinweise",
    "country_name": "Singapur",
    "country_code": "SG",
    "iso3_country_code": "SGP",
    "last_modified_iso": "2025-09-23T14:43:49+00:00",
    "effective_iso": null,
    "warning": 0,
    "partial_warning": 0,
    "situation_warning": 0,
    "situation_part_warning": 0
  },
  {
    "content_id": 226912,
    "title": "Seychellen: Reise- und Sicherheitshinweise",
    "country_name": "Seychellen",
    "country_code": "SC",
    "iso3_country_code": "SYC",
    "last_modified_iso": "2025-03-26T12:13:48+00:00",
    "effective_iso": null,
    "warning": 0,
    "partial_warning": 0,
    "situation_warning": 0,
    "situation_part_warning": 0
  },
  {
    "content_id": 224982,
    "title": "Venezuela: Reise- und Sicherheitshinweise",
    "country_name": "Venezuela",
    "country_code": "VE",
    "iso3_country_code": "VEN",
    "last_modified_iso": "2026-01-07T09:45:35+00:00",
    "effective_iso": null,
    "warning": 1,
    "partial_warning": 0,
    "situation_warning": 0,
    "situation_part_warning": 0
  },
  {
    "content_id": 208662,
    "title": "Tansania: Reise- und Sicherheitshinweise",
    "country_name": "Tansania",
    "country_code": "TZ",
    "iso3_country_code": "TZA",
    "last_modified_iso": "2025-12-12T15:44:18+00:00",
    "effective_iso": null,
    "warning": 0,
    "partial_warning": 0,
    "situation_warning": 0,
    "situation_part_warning": 0
  },
  {
    "content_id": 200896,
    "title": "Taiwan*: Reise- und Sicherheitshinweise",
    "country_name": "Taiwan*",
    "country_code": "TW",
    "iso3_country_code": "TWN",
    "last_modified_iso": "2025-12-01T14:21:36+00:00",
    "effective_iso": null,
    "warning": 0,
    "partial_warning": 0,
    "situation_warning": 0,
    "situation_part_warning": 0
  },
  {
    "content_id": 201962,
    "title": "Türkei: Reise- und Sicherheitshinweise",
    "country_name": "Türkei",
    "country_code": "TR",
    "iso3_country_code": "TUR",
    "last_modified_iso": "2026-01-02T14:14:00+00:00",
    "effective_iso": null,
    "warning": 0,
    "partial_warning": 0,
    "situation_warning": 0,
    "situation_part_warning": 0
  },
  {
    "content_id": 205878,
    "title": "Norwegen: Reise- und Sicherheitshinweise",
    "country_name": "Norwegen",
    "country_code": "NO",
    "iso3_country_code": "NOR",
    "last_modified_iso": "2025-12-01T08:53:53+00:00",
    "effective_iso": null,
    "warning": 0,
    "partial_warning": 0,
    "situation_warning": 0,
    "situation_part_warning": 0
  },
  {
    "content_id": 204874,
    "title": "Kanada: Reise- und Sicherheitshinweise",
    "country_name": "Kanada",
    "country_code": "CA",
    "iso3_country_code": "CAN",
    "last_modified_iso": "2025-11-04T07:57:32+00:00",
    "effective_iso": null,
    "warning": 0,
    "partial_warning": 0,
    "situation_warning": 0,
    "situation_part_warning": 0
  },
  {
    "content_id": 224080,
    "title": "Marokko: Reise- und Sicherheitshinweise",
    "country_name": "Marokko",
    "country_code": "MA",
    "iso3_country_code": "MAR",
    "last_modified_iso": "2025-12-17T09:24:57+00:00",
    "effective_iso": null,
    "warning": 0,
    "partial_warning": 0,
    "situation_warning": 0,
    "situation_part_warning": 0
  },
  {
    "content_id": 204974,
    "title": "Pakistan: Reise- und Sicherheitshinweise",
    "country_name": "Pakistan",
    "country_code": "PK",
    "iso3_country_code": "PAK",
    "last_modified_iso": "2025-11-28T13:42:46+00:00",
    "effective_iso": null,
    "warning": 0,
    "partial_warning": 1,
    "situation_warning": 0,
    "situation_part_warning": 0
  },
  {
    "content_id": 202280,
    "title": "Katar: Reise- und Sicherheitshinweise",
    "country_name": "Katar",
    "country_code": "QA",
    "iso3_country_code": "QAT",
    "last_modified_iso": "2026-01-14T15:38:42+00:00",
    "effective_iso": null,
    "warning": 0,
    "partial_warning": 0,
    "situation_warning": 0,
    "situation_part_warning": 0
  },
  {
    "content_id": 211084,
    "title": "Königreich der Niederlande: Reise- und Sicherheitshinweise",
    "country_name": "Niederlande",
    "country_code": "NL",
    "iso3_country_code": "NLD",
    "last_modified_iso": "2025-11-25T14:03:27+00:00",
    "effective_iso": null,
    "warning": 0,
    "partial_warning": 0,
    "situation_warning": 0,
    "situation_part_warning": 0
  },
  {
    "content_id": 218008,
    "title": "Jordanien: Reise- und Sicherheitshinweise",
    "country_name": "Jordanien",
    "country_code": "JO",
    "iso3_country_code": "JOR",
    "last_modified_iso": "2026-01-14T17:14:18+00:00",
    "effective_iso": null,
    "warning": 0,
    "partial_warning": 0,
    "situation_warning": 0,
    "situation_part_warning": 0
  },
  {
    "content_id": 213648,
    "title": "Mexiko: Reise- und Sicherheitshinweise",
    "country_name": "Mexiko",
    "country_code": "MX",
    "iso3_country_code": "MEX",
    "last_modified_iso": "2025-09-11T13:06:45+00:00",
    "effective_iso": null,
    "warning": 0,
    "partial_warning": 0,
    "situation_warning": 0,
    "situation_part_warning": 0
  },
  {
    "content_id": 201516,
    "title": "Kolumbien: Reise- und Sicherheitshinweise",
    "country_name": "Kolumbien",
    "country_code": "CO",
    "iso3_country_code": "COL",
    "last_modified_iso": "2025-12-02T14:48:20+00:00",
    "effective_iso": null,
    "warning": 0,
    "partial_warning": 1,
    "situation_warning": 0,
    "situation_part_warning": 0
  },
  {
    "content_id": 201382,
    "title": "USA/Vereinigte Staaten: Reise- und Sicherheitshinweise",
    "country_name": "USA",
    "country_code": "US",
    "iso3_country_code": "USA",
    "last_modified_iso": "2025-11-26T15:26:40+00:00",
    "effective_iso": null,
    "warning": 0,
    "partial_warning": 0,
    "situation_warning": 0,
    "situation_part_warning": 0
  },
  {
    "content_id": 208508,
    "title": "Malawi: Reise- und Sicherheitshinweise",
    "country_name": "Malawi",
    "country_code": "MW",
    "iso3_country_code": "MWI",
    "last_modified_iso": "2026-01-15T13:40:31+00:00",
    "effective_iso": null,
    "warning": 0,
    "partial_warning": 0,
    "situation_warning": 0,
    "situation_part_warning": 0
  },
  {
    "content_id": 220450,
    "title": "Suriname: Reise- und Sicherheitshinweise",
    "country_name": "Suriname",
    "country_code": "SR",
    "iso3_country_code": "SUR",
    "last_modified_iso": "2026-01-15T13:35:04+00:00",
    "effective_iso": null,
    "warning": 0,
    "partial_warning": 0,
    "situation_warning": 0,
    "situation_part_warning": 0
  },
  {
    "content_id": 203674,
    "title": "Palästinensische Gebiete: Reise- und Sicherheitshinweise",
    "country_name": "Palästinensische Gebiete*",
    "country_code": "PS",
    "iso3_country_code": "PSE",
    "last_modified_iso": "2026-01-15T20:24:30+00:00",
    "effective_iso": null,
    "warning": 1,
    "partial_warning": 0,
    "situation_warning": 0,
    "situation_part_warning": 0
  },
  {
    "content_id": 219024,
    "title": "Tunesien: Reise- und Sicherheitshinweise",
    "country_name": "Tunesien",
    "country_code": "TN",
    "iso3_country_code": "TUN",
    "last_modified_iso": "2025-12-15T17:26:03+00:00",
    "effective_iso": null,
    "warning": 0,
    "partial_warning": 0,
    "situation_warning": 0,
    "situation_part_warning": 0
  },
  {
    "content_id": 201230,
    "title": "Chile: Reise- und Sicherheitshinweise",
    "country_name": "Chile",
    "country_code": "CL",
    "iso3_country_code": "CHL",
    "last_modified_iso": "2026-01-12T11:08:34+00:00",
    "effective_iso": null,
    "warning": 0,
    "partial_warning": 0,
    "situation_warning": 0,
    "situation_part_warning": 0
  },
  {
    "content_id": 213428,
    "title": "Bolivien: Reise- und Sicherheitshinweise",
    "country_name": "Bolivien",
    "country_code": "BO",
    "iso3_country_code": "BOL",
    "last_modified_iso": "2025-12-17T11:11:04+00:00",
    "effective_iso": null,
    "warning": 0,
    "partial_warning": 0,
    "situation_warning": 0,
    "situation_part_warning": 0
  },
  {
    "content_id": 201326,
    "title": "Argentinien: Reise- und Sicherheitshinweise",
    "country_name": "Argentinien",
    "country_code": "AR",
    "iso3_country_code": "ARG",
    "last_modified_iso": "2026-01-09T16:14:29+00:00",
    "effective_iso": null,
    "warning": 0,
    "partial_warning": 0,
    "situation_warning": 0,
    "situation_part_warning": 0
  },
  {
    "content_id": 216248,
    "title": "Albanien: Reise- und Sicherheitshinweise",
    "country_name": "Albanien",
    "country_code": "AL",
    "iso3_country_code": "ALB",
    "last_modified_iso": "2026-01-13T10:11:33+00:00",
    "effective_iso": null,
    "warning": 0,
    "partial_warning": 0,
    "situation_warning": 0,
    "situation_part_warning": 0
  },
  {
    "content_id": 201092,
    "title": "Brasilien: Reise- und Sicherheitshinweise",
    "country_name": "Brasilien",
    "country_code": "BR",
    "iso3_country_code": "BRA",
    "last_modified_iso": "2026-01-12T10:55:29+00:00",
    "effective_iso": null,
    "warning": 0,
    "partial_warning": 0,
    "situation_warning": 0,
    "situation_part_warning": 0
  },
  {
    "content_id": 226424,
    "title": "Barbados: Reise- und Sicherheitshinweise",
    "country_name": "Barbados",
    "country_code": "BB",
    "iso3_country_code": "BRB",
    "last_modified_iso": "2024-12-10T08:27:36+00:00",
    "effective_iso": null,
    "warning": 0,
    "partial_warning": 0,
    "situation_warning": 0,
    "situation_part_warning": 0
  },
  {
    "content_id": 213920,
    "title": "Australien: Reise- und Sicherheitshinweise",
    "country_name": "Australien",
    "country_code": "AU",
    "iso3_country_code": "AUS",
    "last_modified_iso": "2025-12-17T13:53:09+00:00",
    "effective_iso": null,
    "warning": 0,
    "partial_warning": 0,
    "situation_warning": 0,
    "situation_part_warning": 0
  },
  {
    "content_id": 206146,
    "title": "Dominikanische Republik: Reise- und Sicherheitshinweise",
    "country_name": "Dominikanische Republik",
    "country_code": "DO",
    "iso3_country_code": "DOM",
    "last_modified_iso": "2025-10-27T09:43:37+00:00",
    "effective_iso": null,
    "warning": 0,
    "partial_warning": 0,
    "situation_warning": 0,
    "situation_part_warning": 0
  },
  {
    "content_id": 211724,
    "title": "Dänemark: Reise- und Sicherheitshinweise",
    "country_name": "Dänemark",
    "country_code": "DK",
    "iso3_country_code": "DNK",
    "last_modified_iso": "2025-10-14T12:42:19+00:00",
    "effective_iso": null,
    "warning": 0,
    "partial_warning": 0,
    "situation_warning": 0,
    "situation_part_warning": 0
  },
  {
    "content_id": 219522,
    "title": "Botsuana: Reise- und Sicherheitshinweise",
    "country_name": "Botsuana",
    "country_code": "BW",
    "iso3_country_code": "BWA",
    "last_modified_iso": "2025-11-11T15:38:09+00:00",
    "effective_iso": null,
    "warning": 0,
    "partial_warning": 0,
    "situation_warning": 0,
    "situation_part_warning": 0
  },
  {
    "content_id": 224816,
    "title": "Costa Rica: Reise- und Sicherheitshinweise",
    "country_name": "Costa Rica",
    "country_code": "CR",
    "iso3_country_code": "CRI",
    "last_modified_iso": "2025-07-31T10:35:06+00:00",
    "effective_iso": null,
    "warning": 0,
    "partial_warning": 0,
    "situation_warning": 0,
    "situation_part_warning": 0
  },
  {
    "content_id": 212492,
    "title": "Philippinen: Reise- und Sicherheitshinweise",
    "country_name": "Philippinen",
    "country_code": "PH",
    "iso3_country_code": "PHL",
    "last_modified_iso": "2026-01-14T10:43:54+00:00",
    "effective_iso": null,
    "warning": 0,
    "partial_warning": 1,
    "situation_warning": 0,
    "situation_part_warning": 0
  },
  {
    "content_id": 226490,
    "title": "Jamaika: Reise- und Sicherheitshinweise",
    "country_name": "Jamaika",
    "country_code": "JM",
    "iso3_country_code": "JAM",
    "last_modified_iso": "2026-01-09T15:24:32+00:00",
    "effective_iso": null,
    "warning": 0,
    "partial_warning": 0,
    "situation_warning": 0,
    "situation_part_warning": 0
  },
  {
    "content_id": 206994,
    "title": "Mauritius: Reise- und Sicherheitshinweise",
    "country_name": "Mauritius",
    "country_code": "MU",
    "iso3_country_code": "MUS",
    "last_modified_iso": "2025-10-01T11:25:59+00:00",
    "effective_iso": null,
    "warning": 0,
    "partial_warning": 0,
    "situation_warning": 0,
    "situation_part_warning": 0
  },
  {
    "content_id": 207960,
    "title": "Madagaskar: Reise- und Sicherheitshinweise",
    "country_name": "Madagaskar",
    "country_code": "MG",
    "iso3_country_code": "MDG",
    "last_modified_iso": "2026-01-12T14:53:30+00:00",
    "effective_iso": null,
    "warning": 0,
    "partial_warning": 0,
    "situation_warning": 0,
    "situation_part_warning": 0
  },
  {
    "content_id": 206738,
    "title": "Kirgisistan: Reise- und Sicherheitshinweise",
    "country_name": "Kirgisistan",
    "country_code": "KG",
    "iso3_country_code": "KGZ",
    "last_modified_iso": "2026-01-05T13:51:38+00:00",
    "effective_iso": null,
    "warning": 0,
    "partial_warning": 0,
    "situation_warning": 0,
    "situation_part_warning": 0
  },
  {
    "content_id": 221216,
    "title": "Nepal: Reise- und Sicherheitshinweise",
    "country_name": "Nepal",
    "country_code": "NP",
    "iso3_country_code": "NPL",
    "last_modified_iso": "2025-11-21T11:14:44+00:00",
    "effective_iso": null,
    "warning": 0,
    "partial_warning": 0,
    "situation_warning": 0,
    "situation_part_warning": 0
  },
  {
    "content_id": 208314,
    "title": "Namibia: Reise- und Sicherheitshinweise",
    "country_name": "Namibia",
    "country_code": "NA",
    "iso3_country_code": "NAM",
    "last_modified_iso": "2026-01-02T13:38:40+00:00",
    "effective_iso": null,
    "warning": 0,
    "partial_warning": 0,
    "situation_warning": 0,
    "situation_part_warning": 0
  },
  {
    "content_id": 206378,
    "title": "Panama: Reise- und Sicherheitshinweise",
    "country_name": "Panama",
    "country_code": "PA",
    "iso3_country_code": "PAN",
    "last_modified_iso": "2025-12-19T13:51:44+00:00",
    "effective_iso": null,
    "warning": 0,
    "partial_warning": 0,
    "situation_warning": 0,
    "situation_part_warning": 0
  },
  {
    "content_id": 223316,
    "title": "Nicaragua: Reise- und Sicherheitshinweise",
    "country_name": "Nicaragua",
    "country_code": "NI",
    "iso3_country_code": "NIC",
    "last_modified_iso": "2025-09-23T15:18:02+00:00",
    "effective_iso": null,
    "warning": 0,
    "partial_warning": 0,
    "situation_warning": 0,
    "situation_part_warning": 0
  },
  {
    "content_id": 204160,
    "title": "Oman: Reise- und Sicherheitshinweise",
    "country_name": "Oman",
    "country_code": "OM",
    "iso3_country_code": "OMN",
    "last_modified_iso": "2026-01-14T15:40:09+00:00",
    "effective_iso": null,
    "warning": 0,
    "partial_warning": 0,
    "situation_warning": 0,
    "situation_part_warning": 0
  },
  {
    "content_id": 206342,
    "title": "Kasachstan: Reise- und Sicherheitshinweise",
    "country_name": "Kasachstan",
    "country_code": "KZ",
    "iso3_country_code": "KAZ",
    "last_modified_iso": "2025-08-29T13:55:18+00:00",
    "effective_iso": null,
    "warning": 0,
    "partial_warning": 0,
    "situation_warning": 0,
    "situation_part_warning": 0
  },
  {
    "content_id": 211938,
    "title": "Peru: Reise- und Sicherheitshinweise",
    "country_name": "Peru",
    "country_code": "PE",
    "iso3_country_code": "PER",
    "last_modified_iso": "2025-12-22T14:36:50+00:00",
    "effective_iso": null,
    "warning": 0,
    "partial_warning": 0,
    "situation_warning": 0,
    "situation_part_warning": 0
  },
  {
    "content_id": 216132,
    "title": "Republik Korea (Südkorea): Reise- und Sicherheitshinweise",
    "country_name": "Republik Korea (Südkorea)",
    "country_code": "KR",
    "iso3_country_code": "KOR",
    "last_modified_iso": "2026-01-13T15:45:25+00:00",
    "effective_iso": null,
    "warning": 0,
    "partial_warning": 0,
    "situation_warning": 0,
    "situation_part_warning": 0
  },
  {
    "content_id": 212208,
    "title": "Kuba: Reise- und Sicherheitshinweise",
    "country_name": "Kuba",
    "country_code": "CU",
    "iso3_country_code": "CUB",
    "last_modified_iso": "2025-12-19T11:30:14+00:00",
    "effective_iso": null,
    "warning": 0,
    "partial_warning": 0,
    "situation_warning": 0,
    "situation_part_warning": 0
  },
  {
    "content_id": 208058,
    "title": "Kenia: Reise- und Sicherheitshinweise",
    "country_name": "Kenia",
    "country_code": "KE",
    "iso3_country_code": "KEN",
    "last_modified_iso": "2026-01-07T13:17:00+00:00",
    "effective_iso": null,
    "warning": 0,
    "partial_warning": 0,
    "situation_warning": 0,
    "situation_part_warning": 0
  },
  {
    "content_id": 211460,
    "title": "Irland: Reise- und Sicherheitshinweise",
    "country_name": "Irland",
    "country_code": "IE",
    "iso3_country_code": "IRL",
    "last_modified_iso": "2025-10-14T12:46:30+00:00",
    "effective_iso": null,
    "warning": 0,
    "partial_warning": 0,
    "situation_warning": 0,
    "situation_part_warning": 0
  },
  {
    "content_id": 220146,
    "title": "Neuseeland: Reise- und Sicherheitshinweise",
    "country_name": "Neuseeland",
    "country_code": "NZ",
    "iso3_country_code": "NZL",
    "last_modified_iso": "2025-07-11T12:45:04+00:00",
    "effective_iso": null,
    "warning": 0,
    "partial_warning": 0,
    "situation_warning": 0,
    "situation_part_warning": 0
  },
  {
    "content_id": 223616,
    "title": "Malaysia: Reise- und Sicherheitshinweise",
    "country_name": "Malaysia",
    "country_code": "MY",
    "iso3_country_code": "MYS",
    "last_modified_iso": "2026-01-05T10:56:59+00:00",
    "effective_iso": null,
    "warning": 0,
    "partial_warning": 0,
    "situation_warning": 0,
    "situation_part_warning": 0
  },
  {
    "content_id": 203814,
    "title": "Israel: Reise- und Sicherheitshinweise (Palästinensische Gebiete - Gazastreifen)",
    "country_name": "Israel",
    "country_code": "IL",
    "iso3_country_code": "ISR",
    "last_modified_iso": "2026-01-15T20:22:19+00:00",
    "effective_iso": null,
    "warning": 0,
    "partial_warning": 0,
    "situation_warning": 0,
    "situation_part_warning": 0
  },
  {
    "content_id": 202298,
    "title": "Saudi-Arabien: Reise- und Sicherheitshinweise",
    "country_name": "Saudi-Arabien",
    "country_code": "SA",
    "iso3_country_code": "SAU",
    "last_modified_iso": "2026-01-14T15:43:51+00:00",
    "effective_iso": null,
    "warning": 0,
    "partial_warning": 0,
    "situation_warning": 0,
    "situation_part_warning": 0
  },
  {
    "content_id": 210534,
    "title": "Spanien: Reise- und Sicherheitshinweise",
    "country_name": "Spanien",
    "country_code": "ES",
    "iso3_country_code": "ESP",
    "last_modified_iso": "2025-12-08T17:26:41+00:00",
    "effective_iso": null,
    "warning": 0,
    "partial_warning": 0,
    "situation_warning": 0,
    "situation_part_warning": 0
  },
  {
    "content_id": 217274,
    "title": "Vietnam: Reise- und Sicherheitshinweise",
    "country_name": "Vietnam",
    "country_code": "VN",
    "iso3_country_code": "VNM",
    "last_modified_iso": "2026-01-05T11:38:27+00:00",
    "effective_iso": null,
    "warning": 0,
    "partial_warning": 0,
    "situation_warning": 0,
    "situation_part_warning": 0
  },
  {
    "content_id": 208400,
    "title": "Südafrika: Reise- und Sicherheitshinweise",
    "country_name": "Südafrika",
    "country_code": "ZA",
    "iso3_country_code": "ZAF",
    "last_modified_iso": "2026-01-15T10:01:56+00:00",
    "effective_iso": null,
    "warning": 0,
    "partial_warning": 0,
    "situation_warning": 0,
    "situation_part_warning": 0
  },
  {
    "content_id": 201558,
    "title": "Thailand: Reise- und Sicherheitshinweise",
    "country_name": "Thailand",
    "country_code": "TH",
    "iso3_country_code": "THA",
    "last_modified_iso": "2026-01-05T11:25:22+00:00",
    "effective_iso": null,
    "warning": 0,
    "partial_warning": 1,
    "situation_warning": 0,
    "situation_part_warning": 0
  },
  {
    "content_id": 201536,
    "title": "Russische Föderation: Reise- und Sicherheitshinweise",
    "country_name": "Russische Föderation",
    "country_code": "RU",
    "iso3_country_code": "RUS",
    "last_modified_iso": "2025-11-25T15:06:08+00:00",
    "effective_iso": null,
    "warning": 0,
    "partial_warning": 1,
    "situation_warning": 0,
    "situation_part_warning": 0
  },
  {
    "content_id": 208118,
    "title": "Angola: Reise- und Sicherheitshinweise",
    "country_name": "Angola",
    "country_code": "AO",
    "iso3_country_code": "AGO",
    "last_modified_iso": "2026-01-16T10:51:03+00:00",
    "effective_iso": null,
    "warning": 0,
    "partial_warning": 0,
    "situation_warning": 0,
    "situation_part_warning": 0
  },
  {
    "content_id": 226240,
    "title": "Eswatini: Reise- und Sicherheitshinweise",
    "country_name": "Eswatini",
    "country_code": "SZ",
    "iso3_country_code": "SWZ",
    "last_modified_iso": "2026-01-16T10:28:06+00:00",
    "effective_iso": null,
    "warning": 0,
    "partial_warning": 0,
    "situation_warning": 0,
    "situation_part_warning": 0
  },
  {
    "content_id": 220332,
    "title": "Guinea-Bissau: Reise- und Sicherheitshinweise",
    "country_name": "Guinea-Bissau",
    "country_code": "GW",
    "iso3_country_code": "GNB",
    "last_modified_iso": "2026-01-16T14:18:08+00:00",
    "effective_iso": null,
    "warning": 0,
    "partial_warning": 0,
    "situation_warning": 0,
    "situation_part_warning": 0
  },
  {
    "content_id": 220008,
    "title": "Kambodscha: Reise- und Sicherheitshinweise",
    "country_name": "Kambodscha",
    "country_code": "KH",
    "iso3_country_code": "KHM",
    "last_modified_iso": "2026-01-16T15:00:54+00:00",
    "effective_iso": null,
    "warning": 0,
    "partial_warning": 1,
    "situation_warning": 0,
    "situation_part_warning": 0
  }
]